pdm_version.py
pdm_version-2.1.0.dist-info/entry_points.txt
pdm_version-2.1.0.dist-info/WHEEL
pdm_version-2.1.0.dist-info/METADATA
pdm_version-2.1.0.dist-info/licenses/LICENSE
pdm_version-2.1.0.dist-info/RECORD
