Metadata-Version: 2.1
Name: pdm-version
Version: 2.1.0
Summary: Make `pdm version` like `poetry version`
License: Apache2.0
Author-email: abersheeran <me@abersheeran.com>
Requires-Python: >=3.7
Requires-Dist: pdm<3.0,>=2.3.1
Project-URL: homepage, https://github.com/abersheeran/pdm-version
